{"department":"Informatics","assistants":[{"name":"Assistant_1","minimumHoursPerWeek":0,"maximumHoursPerWeek":12,"maximumDaysPerWeek":3,"maximumHoursTotal":312,"skills":[{"name":"4CCS1FCOM","preference":0},{"name":"4CCS1DBS","preference":2},{"name":"4CCS1PRP","preference":2},{"name":"5CCS2OS","preference":2},{"name":"5CCS2SEG","preference":2},{"name":"6CCS3ML","preference":1},{"name":"6CCS3ALG","preference":2}],"blockedDates":["Week_23_Thursday"]},{"name":"Assistant_2","minimumHoursPerWeek":0,"maximumHoursPerWeek":6,"maximumDaysPerWeek":3,"maximumHoursTotal":312,"skills":[{"name":"4CCS1FCOM","preference":2},{"name":"4CCS1DBS","preference":2},{"name":"4CCS1PRP","preference":1},{"name":"5CCS2OS","preference":0},{"name":"5CCS2SEG","preference":2},{"name":"6CCS3ML","preference":2},{"name":"6CCS3ALG","preference":2}],"blockedDates":["Week_23_Wednesday"]},{"name":"Assistant_3","minimumHoursPerWeek":0,"maximumHoursPerWeek":13,"maximumDaysPerWeek":3,"maximumHoursTotal":312,"skills":[{"name":"4CCS1FCOM","preference":0},{"name":"4CCS1DBS","preference":2},{"name":"4CCS1PRP","preference":2},{"name":"5CCS2OS","preference":2},{"name":"5CCS2SEG","preference":2},{"name":"6CCS3ML","preference":2},{"name":"6CCS3ALG","preference":2}],"blockedDates":[]},{"name":"Assistant_4","minimumHoursPerWeek":0,"maximumHoursPerWeek":6,"maximumDaysPerWeek":3,"maximumHoursTotal":312,"skills":[{"name":"4CCS1FCOM","preference":2},{"name":"4CCS1DBS","preference":1},{"name":"4CCS1PRP","preference":0},{"name":"5CCS2OS","preference":2},{"name":"5CCS2SEG","preference":1},{"name":"6CCS3ML","preference":2},{"name":"6CCS3ALG","preference":2}],"blockedDates":["Week_25_Monday"]},{"name":"Assistant_5","minimumHoursPerWeek":0,"maximumHoursPerWeek":10,"maximumDaysPerWeek":3,"maximumHoursTotal":312,"skills":[{"name":"4CCS1FCOM","preference":1},{"name":"4CCS1DBS","preference":1},{"name":"4CCS1PRP","preference":0},{"name":"5CCS2OS","preference":1},{"name":"5CCS2SEG","preference":0},{"name":"6CCS3ML","preference":2},{"name":"6CCS3ALG","preference":0}],"blockedDates":["Week_26_Monday"]},{"name":"Assistant_6","minimumHoursPerWeek":0,"maximumHoursPerWeek":19,"maximumDaysPerWeek":3,"maximumHoursTotal":312,"skills":[{"name":"4CCS1FCOM","preference":2},{"name":"4CCS1DBS","preference":0},{"name":"4CCS1PRP","preference":1},{"name":"5CCS2OS","preference":2},{"name":"5CCS2SEG","preference":1},{"name":"6CCS3ML","preference":1},{"name":"6CCS3ALG","preference":0}],"blockedDates":["Week_26_Tuesday"]},{"name":"Assistant_7","minimumHoursPerWeek":0,"maximumHoursPerWeek":7,"maximumDaysPerWeek":3,"maximumHoursTotal":312,"skills":[{"name":"4CCS1FCOM","preference":2},{"name":"4CCS1DBS","preference":1},{"name":"4CCS1PRP","preference":0},{"name":"5CCS2OS","preference":2},{"name":"5CCS2SEG","preference":1},{"name":"6CCS3ML","preference":2},{"name":"6CCS3ALG","preference":2}],"blockedDates":[]},{"name":"Assistant_8","minimumHoursPerWeek":0,"maximumHoursPerWeek":6,"maximumDaysPerWeek":3,"maximumHoursTotal":312,"skills":[{"name":"4CCS1FCOM","preference":2},{"name":"4CCS1DBS","preference":0},{"name":"4CCS1PRP","preference":1},{"name":"5CCS2OS","preference":1},{"name":"5CCS2SEG","preference":1},{"name":"6CCS3ML","preference":0},{"name":"6CCS3ALG","preference":0}],"blockedDates":["Week_23_Friday"]},{"name":"Assistant_9","minimumHoursPerWeek":0,"maximumHoursPerWeek":18,"maximumDaysPerWeek":3,"maximumHoursTotal":312,"skills":[{"name":"4CCS1FCOM","preference":1},{"name":"4CCS1DBS","preference":1},{"name":"4CCS1PRP","preference":0},{"name":"5CCS2OS","preference":1},{"name":"5CCS2SEG","preference":0},{"name":"6CCS3ML","preference":1},{"name":"6CCS3ALG","preference":0}],"blockedDates":[]},{"name":"Assistant_10","minimumHoursPerWeek":0,"maximumHoursPerWeek":17,"maximumDaysPerWeek":3,"maximumHoursTotal":312,"skills":[{"name":"4CCS1FCOM","preference":1},{"name":"4CCS1DBS","preference":0},{"name":"4CCS1PRP","preference":0},{"name":"5CCS2OS","preference":0},{"name":"5CCS2SEG","preference":0},{"name":"6CCS3ML","preference":2},{"name":"6CCS3ALG","preference":0}],"blockedDates":["Week_25_Wednesday"]}],"tutorials":[],"timeslots":[{"id":0,"day":"Week_23_Monday","name":"0"},{"id":5,"day":"Week_23_Monday","name":"5"},{"id":1,"day":"Week_23_Tuesday","name":"1"},{"id":6,"day":"Week_23_Tuesday","name":"6"},{"id":2,"day":"Week_23_Wednesday","name":"2"},{"id":7,"day":"Week_23_Wednesday","name":"7"},{"id":3,"day":"Week_23_Thursday","name":"3"},{"id":8,"day":"Week_23_Thursday","name":"8"},{"id":4,"day":"Week_23_Friday","name":"4"},{"id":9,"day":"Week_23_Friday","name":"9"},{"id":10,"day":"Week_24_Monday","name":"10"},{"id":15,"day":"Week_24_Monday","name":"15"},{"id":11,"day":"Week_24_Tuesday","name":"11"},{"id":16,"day":"Week_24_Tuesday","name":"16"},{"id":12,"day":"Week_24_Wednesday","name":"12"},{"id":17,"day":"Week_24_Wednesday","name":"17"},{"id":13,"day":"Week_24_Thursday","name":"13"},{"id":18,"day":"Week_24_Thursday","name":"18"},{"id":14,"day":"Week_24_Friday","name":"14"},{"id":19,"day":"Week_24_Friday","name":"19"},{"id":20,"day":"Week_25_Monday","name":"20"},{"id":25,"day":"Week_25_Monday","name":"25"},{"id":21,"day":"Week_25_Tuesday","name":"21"},{"id":26,"day":"Week_25_Tuesday","name":"26"},{"id":22,"day":"Week_25_Wednesday","name":"22"},{"id":27,"day":"Week_25_Wednesday","name":"27"},{"id":23,"day":"Week_25_Thursday","name":"23"},{"id":28,"day":"Week_25_Thursday","name":"28"},{"id":24,"day":"Week_25_Friday","name":"24"},{"id":29,"day":"Week_25_Friday","name":"29"},{"id":30,"day":"Week_26_Monday","name":"30"},{"id":35,"day":"Week_26_Monday","name":"35"},{"id":31,"day":"Week_26_Tuesday","name":"31"},{"id":36,"day":"Week_26_Tuesday","name":"36"},{"id":32,"day":"Week_26_Wednesday","name":"32"},{"id":37,"day":"Week_26_Wednesday","name":"37"},{"id":33,"day":"Week_26_Thursday","name":"33"},{"id":38,"day":"Week_26_Thursday","name":"38"},{"id":34,"day":"Week_26_Friday","name":"34"},{"id":39,"day":"Week_26_Friday","name":"39"}],"lecturers":[{"name":"Lecturer_1","tutorials":["4CCS1FCOM_Tutorial_Group1","4CCS1FCOM_Tutorial_Group2","4CCS1FCOM_Tutorial_Group3","4CCS1FCOM_Tutorial_Group4","4CCS1FCOM_Lab_Group1","4CCS1FCOM_Lab_Group2","4CCS1FCOM_Lab_Group3","4CCS1FCOM_Lab_Group4"],"skillTypeName":"4CCS1FCOM","maximumNumberOfTas":6},{"name":"Lecturer_2","tutorials":["4CCS1DBS_Tutorial_Group1","4CCS1DBS_Tutorial_Group2","4CCS1DBS_Tutorial_Group3","4CCS1DBS_Tutorial_Group4","4CCS1DBS_Lab_Group1","4CCS1DBS_Lab_Group2","4CCS1DBS_Lab_Group3","4CCS1DBS_Lab_Group4"],"skillTypeName":"4CCS1DBS","maximumNumberOfTas":7},{"name":"Lecturer_3","tutorials":["4CCS1PRP_Tutorial_Group1","4CCS1PRP_Tutorial_Group2","4CCS1PRP_Tutorial_Group3","4CCS1PRP_Lab_Group1","4CCS1PRP_Lab_Group2","4CCS1PRP_Lab_Group3"],"skillTypeName":"4CCS1PRP","maximumNumberOfTas":2},{"name":"Lecturer_4","tutorials":["5CCS2OS_Tutorial_Group1","5CCS2OS_Tutorial_Group2","5CCS2OS_Tutorial_Group3","5CCS2OS_Tutorial_Group4","5CCS2OS_Tutorial_Group5"],"skillTypeName":"5CCS2OS","maximumNumberOfTas":5},{"name":"Lecturer_5","tutorials":["5CCS2SEG_Lab_Group1","5CCS2SEG_Lab_Group2","5CCS2SEG_Lab_Group3","5CCS2SEG_Lab_Group4","5CCS2SEG_Lab_Group5"],"skillTypeName":"5CCS2SEG","maximumNumberOfTas":6},{"name":"Lecturer_6","tutorials":["6CCS3ML_Tutorial_Group1","6CCS3ML_Tutorial_Group2","6CCS3ML_Tutorial_Group3","6CCS3ML_Tutorial_Group4"],"skillTypeName":"6CCS3ML","maximumNumberOfTas":3},{"name":"Lecturer_7","tutorials":["6CCS3ALG_Lab_Group1","6CCS3ALG_Lab_Group2","6CCS3ALG_Lab_Group3","6CCS3ALG_Lab_Group4"],"skillTypeName":"6CCS3ALG","maximumNumberOfTas":5}],"modules":[{"code":"4CCS1FCOM","name":"Foundations of Computing","lecturer":"Lecturer_1","maximumNumberOfTas":6,"sessions":[]},{"code":"4CCS1DBS","name":"Database Systems","lecturer":"Lecturer_2","maximumNumberOfTas":7,"sessions":[]},{"code":"4CCS1PRP","name":"Programming Practice","lecturer":"Lecturer_3","maximumNumberOfTas":2,"sessions":[]},{"code":"5CCS2OS","name":"Operating Systems","lecturer":"Lecturer_4","maximumNumberOfTas":5,"sessions":[]},{"code":"5CCS2SEG","name":"Software Engineering","lecturer":"Lecturer_5","maximumNumberOfTas":6,"sessions":[]},{"code":"6CCS3ML","name":"Machine Learning","lecturer":"Lecturer_6","maximumNumberOfTas":3,"sessions":[]},{"code":"6CCS3ALG","name":"Algorithms","lecturer":"Lecturer_7","maximumNumberOfTas":5,"sessions":[]}],"days":[{"name":"Week_23_Monday","timeslots":[0,5],"week":"Week_23"},{"name":"Week_23_Tuesday","timeslots":[1,6],"week":"Week_23"},{"name":"Week_23_Wednesday","timeslots":[2,7],"week":"Week_23"},{"name":"Week_23_Thursday","timeslots":[3,8],"week":"Week_23"},{"name":"Week_23_Friday","timeslots":[4,9],"week":"Week_23"},{"name":"Week_24_Monday","timeslots":[10,15],"week":"Week_24"},{"name":"Week_24_Tuesday","timeslots":[11,16],"week":"Week_24"},{"name":"Week_24_Wednesday","timeslots":[12,17],"week":"Week_24"},{"name":"Week_24_Thursday","timeslots":[13,18],"week":"Week_24"},{"name":"Week_24_Friday","timeslots":[14,19],"week":"Week_24"},{"name":"Week_25_Monday","timeslots":[20,25],"week":"Week_25"},{"name":"Week_25_Tuesday","timeslots":[21,26],"week":"Week_25"},{"name":"Week_25_Wednesday","timeslots":[22,27],"week":"Week_25"},{"name":"Week_25_Thursday","timeslots":[23,28],"week":"Week_25"},{"name":"Week_25_Friday","timeslots":[24,29],"week":"Week_25"},{"name":"Week_26_Monday","timeslots":[30,35],"week":"Week_26"},{"name":"Week_26_Tuesday","timeslots":[31,36],"week":"Week_26"},{"name":"Week_26_Wednesday","timeslots":[32,37],"week":"Week_26"},{"name":"Week_26_Thursday","timeslots":[33,38],"week":"Week_26"},{"name":"Week_26_Friday","timeslots":[34,39],"week":"Week_26"}],"weeks":[{"name":"Week_23","days":["Week_23_Monday","Week_23_Tuesday","Week_23_Wednesday","Week_23_Thursday","Week_23_Friday"]},{"name":"Week_24","days":["Week_24_Monday","Week_24_Tuesday","Week_24_Wednesday","Week_24_Thursday","Week_24_Friday"]},{"name":"Week_25","days":["Week_25_Monday","Week_25_Tuesday","Week_25_Wednesday","Week_25_Thursday","Week_25_Friday"]},{"name":"Week_26","days":["Week_26_Monday","Week_26_Tuesday","Week_26_Wednesday","Week_26_Thursday","Week_26_Friday"]}]}